setup.py
rango/__init__.py
rango/crypto.py
rango/exceptions.py
rango/forms.py
rango/logging.py
rango/mail.py
rango/models.py
rango/paginator.py
rango/response.py
rango/settings.py
rango/template.py
rango/translation.py
rango/urls.py
rango/utils.py
rango/validation.py
rango/views.py
rango.egg-info/PKG-INFO
rango.egg-info/SOURCES.txt
rango.egg-info/dependency_links.txt
rango.egg-info/requires.txt
rango.egg-info/top_level.txt
rango/auth/__init__.py
rango/auth/models.py
rango/auth/views.py
rango/db/__init__.py
rango/db/models.py