Metadata-Version: 1.1
Name: rango
Version: 0.0.2a
Summary: Rango is a spicey API to Django with some extras.
Home-page: https://github.com/05bit/rango
Author: Alexey Kinyov
Author-email: rudy@05bit.com
License: MIT
Keywords: django,utils,sugar
Platform: UNKNOWN
Classifier: Development Status :: 2 - Pre-Alpha
Classifier: Operating System :: OS Independent
Classifier: License :: OSI Approved :: BSD License
Classifier: Intended Audience :: Developers
Classifier: Environment :: Web Environment
Classifier: Framework :: Django
Classifier: Intended Audience :: Developers
Classifier: Programming Language :: Python :: 2.5
Classifier: Programming Language :: Python :: 2.6
Classifier: Programming Language :: Python :: 2.7
